redis_property.py
redis_property-1.8.2.dist-info/LICENSE
redis_property-1.8.2.dist-info/METADATA
redis_property-1.8.2.dist-info/WHEEL
redis_property-1.8.2.dist-info/top_level.txt
redis_property-1.8.2.dist-info/RECORD
