Metadata-Version: 2.1
Name: redis-property
Version: 1.8.2
Summary: A decorator for caching properties in Redis.
Home-page: https://github.com/Ed-XCF/redis-property
Author: Ed__xu__Ed
Author-email: m.tofu@qq.com
License: UNKNOWN
Platform: UNKNOWN
Classifier: Programming Language :: Python :: 3
Classifier: License :: OSI Approved :: MIT License
Classifier: Operating System :: OS Independent
Requires-Python: >=3.7
Requires-Dist: redis
Requires-Dist: orjson
